personal_mcp/__init__.py
personal_mcp/__main__.py
personal_mcp/cli.py
personal_mcp/database.py
personal_mcp/models.py
personal_mcp/prompts.py
personal_mcp/resources.py
personal_mcp/server.py
personal_mcp/tools/__init__.py
personal_mcp/tools/journal.py
personal_mcp/tools/nutrition.py
personal_mcp/tools/workout.py
personal_mcp-0.1.5.dist-info/METADATA
personal_mcp-0.1.5.dist-info/WHEEL
personal_mcp-0.1.5.dist-info/entry_points.txt
personal_mcp-0.1.5.dist-info/RECORD
