Metadata-Version: 2.4
Name: personal-mcp
Version: 0.1.5
Summary: Personal MCP server for health and well-being tracking
Project-URL: Homepage, https://github.com/estav/personal-mcp
Project-URL: Repository, https://github.com/estav/personal-mcp.git
Project-URL: Bug Tracker, https://github.com/estav/personal-mcp/issues
Author-email: Estav <estav@example.com>
License-Expression: MIT
Keywords: health,mcp,personal,tracking,well-being
Classifier: Development Status :: 3 - Alpha
Classifier: Intended Audience :: End Users/Desktop
Classifier: License :: OSI Approved :: MIT License
Classifier: Programming Language :: Python :: 3
Classifier: Programming Language :: Python :: 3.10
Classifier: Programming Language :: Python :: 3.11
Requires-Python: >=3.10
Requires-Dist: click>=8.0.0
Requires-Dist: mcp>=1.2.0
Requires-Dist: pandas>=2.0.0
Requires-Dist: pydantic>=2.0.0
Requires-Dist: rich>=10.0.0
Requires-Dist: setuptools>=42.0.0
Requires-Dist: wheel>=0.37.0
Provides-Extra: dev
Requires-Dist: black; extra == 'dev'
Requires-Dist: mypy; extra == 'dev'
Requires-Dist: pre-commit; extra == 'dev'
Requires-Dist: pytest-asyncio; extra == 'dev'
Requires-Dist: pytest-cov; extra == 'dev'
Requires-Dist: pytest>=8.3.4; extra == 'dev'
Requires-Dist: ruff; extra == 'dev'
